[
    {
        "IconClass":"fa-regular fa-phone",
        "IconURL":"assets/img/getintouch/telephone.svg",
        "Title":"Telephone",
        "Content":"<a class='link-light text-decoration-none fw-bold' href='tel:+9651806806'>+965 1 806 806</a>"
    },
    {
        "IconClass":"fa-regular fa-envelope",
        "IconURL":"assets/img/getintouch/envelope.svg",
        "Title":"Email",
        "Content":"<a class='link-light text-decoration-none fw-bold' href='mailto:info@tec.com.kw'>info@tec.com.kw</a>"
    },
    {
        "IconClass":"fa-regular fa-pin",
        "IconURL":"assets/img/getintouch/location.svg",
        "Title":"Address",
        "Content":"<a href='javascript:;' class='link-light text-decoration-none fw-bold text-center text-lg-start' href='#'>Al-Jahra Street, Shuwaikh Administrative, Kuwait</a>"
    }
]